omicverse/.DS_Store
omicverse/__init__.py
omicverse/_lazy_loader.py
omicverse/_settings.py
omicverse/.ipynb_checkpoints/__init__-checkpoint.py
omicverse/agent/__init__.py
omicverse/alignment/__init__.py
omicverse/alignment/kb_api.py
omicverse/bulk/.DS_Store
omicverse/bulk/_Deseq2.py
omicverse/bulk/_Enrichment.py
omicverse/bulk/_Gene_module.py
omicverse/bulk/__init__.py
omicverse/bulk/_chm13.py
omicverse/bulk/_combat.py
omicverse/bulk/_decov.py
omicverse/bulk/_df_apply.py
omicverse/bulk/_dynamicTree.py
omicverse/bulk/_network.py
omicverse/bulk/_tcga.py
omicverse/bulk/_alignment/README_ENHANCED.md
omicverse/bulk/_alignment/__init__.py
omicverse/bulk/_alignment/alignment.py
omicverse/bulk/_alignment/count_step.py
omicverse/bulk/_alignment/count_tools.py
omicverse/bulk/_alignment/data_prepare_pipline.py
omicverse/bulk/_alignment/entrez_direct.py
omicverse/bulk/_alignment/geo_meta_fetcher.py
omicverse/bulk/_alignment/iseq_handler.py
omicverse/bulk/_alignment/pipeline_config.py
omicverse/bulk/_alignment/qc_fastp.py
omicverse/bulk/_alignment/qc_tools.py
omicverse/bulk/_alignment/sra_fasterq.py
omicverse/bulk/_alignment/sra_prefetch.py
omicverse/bulk/_alignment/sra_tools.py
omicverse/bulk/_alignment/star_step.py
omicverse/bulk/_alignment/star_tools.py
omicverse/bulk/_alignment/tools_check.py
omicverse/bulk2single/__init__.py
omicverse/bulk2single/_bulk2single.py
omicverse/bulk2single/_bulkdeconvolve.py
omicverse/bulk2single/_bulktrajblend.py
omicverse/bulk2single/_map_utils.py
omicverse/bulk2single/_map_utils1.py
omicverse/bulk2single/_scsemi.py
omicverse/bulk2single/_single2spatial.py
omicverse/bulk2single/_utils.py
omicverse/bulk2single/_vae.py
omicverse/data_files/.DS_Store
omicverse/data_files/README.md
omicverse/data_files/apoptosis_human.gmt
omicverse/data_files/apoptosis_mouse.gmt
omicverse/data_files/c2.cp.v7.5.1.symbols.gmt
omicverse/data_files/cell_cycle_human.gmt
omicverse/data_files/cell_cycle_mouse.gmt
omicverse/data_files/emt_human.gmt
omicverse-1.7.8.dist-info/entry_points.txt
omicverse-1.7.8.dist-info/licenses/LICENSE
omicverse-1.7.8.dist-info/WHEEL
omicverse-1.7.8.dist-info/METADATA
omicverse-1.7.8.dist-info/RECORD
