Metadata-Version: 2.4
Name: omicverse
Version: 1.7.8
Summary: OmicVerse: A single pipeline for exploring the entire transcriptome universe
Keywords: bioinformatics,deep-learning,scRNA-seq,RNA-seq
Author-email: Zehua Zeng <starlitnightly@gmail.com>
Requires-Python: >=3.8
Classifier: Intended Audience :: Science/Research
Classifier: Natural Language :: English
Classifier: Operating System :: MacOS :: MacOS X
Classifier: Operating System :: POSIX :: Linux
Classifier: Programming Language :: Python :: 3
Classifier: Programming Language :: Python :: 3.8
Classifier: Programming Language :: Python :: 3.9
Classifier: Programming Language :: Python :: 3.10
Classifier: Programming Language :: Python :: 3.11
Classifier: Programming Language :: Python :: 3.12
Classifier: Topic :: Scientific/Engineering :: Bio-Informatics
License-File: LICENSE
Requires-Dist: tomli
Requires-Dist: numpy>=1.23
Requires-Dist: scanpy>=1.9
Requires-Dist: pandas>=1.5
Requires-Dist: matplotlib>3.6
Requires-Dist: scikit-learn>=1.2
Requires-Dist: scipy>=1.8, <1.12
Requires-Dist: networkx>=2.8
Requires-Dist: multiprocess>=0.70
Requires-Dist: seaborn>=0.11
Requires-Dist: datetime>=4.5
Requires-Dist: statsmodels>=0.13
Requires-Dist: ipywidgets>=8.0
Requires-Dist: lifelines>=0.27
Requires-Dist: ktplotspy>=0.1
Requires-Dist: python-dotplot>=0.0.1
Requires-Dist: boltons>=23.0
Requires-Dist: ctxcore>=0.2
Requires-Dist: termcolor>=2.1
Requires-Dist: pygam>=0.8.0
Requires-Dist: pillow>=9.0
Requires-Dist: gdown>=4.6
Requires-Dist: igraph>=0.10
Requires-Dist: leidenalg>=0.9
Requires-Dist: graphtools>=1.5
Requires-Dist: tqdm>=4.64
Requires-Dist: pydeseq2>=0.4.1
Requires-Dist: mofax>=0.3
Requires-Dist: adjustText>=0.8
Requires-Dist: scikit-misc>=0.1
Requires-Dist: metatime>=1.3.0
Requires-Dist: einops>=0.6
Requires-Dist: tensorboard>=2.6
Requires-Dist: pynvml
Requires-Dist: plotly
Requires-Dist: numba>=0.56
Requires-Dist: tqdm
Requires-Dist: requests>=2.0
Requires-Dist: transformers>=0.30
Requires-Dist: marsilea
Requires-Dist: wandb
Requires-Dist: dynamo-release ; extra == "full"
Requires-Dist: squidpy ; extra == "full"
Requires-Dist: tangram-sc ; extra == "full"
Requires-Dist: pertpy ; extra == "full"
Requires-Dist: toytree ; extra == "full"
Requires-Dist: arviz ; extra == "full"
Requires-Dist: ete3 ; extra == "full"
Requires-Dist: scvi-tools ; extra == "full"
Requires-Dist: pymde ; extra == "full"
Requires-Dist: torchdr ; extra == "full"
Requires-Dist: memento-de ; extra == "full"
Requires-Dist: beautifulsoup4>=4.12 ; extra == "skillseeker"
Requires-Dist: PyGithub>=2.2 ; extra == "skillseeker"
Requires-Dist: PyMuPDF>=1.24 ; extra == "skillseeker"
Project-URL: Github, https://github.com/Starlitnightly/omicverse
Provides-Extra: full
Provides-Extra: skillseeker
